{
  "$schema": "https://developer.microsoft.com/json-schemas/fabric/item/report/definition/visualContainer/2.9.0/schema.json",
  "name": "bbd02761328c30a6af27",
  "position": {
    "x": 972.64066836749,
    "y": 20,
    "z": 11000,
    "height": 120.57528946704421,
    "width": 240.0022428439261,
    "tabOrder": 11000
  },
  "visual": {
    "visualType": "slicer",
    "query": {
      "queryState": {
        "Values": {
          "projections": [
            {
              "field": {
                "Column": {
                  "Expression": {
                    "SourceRef": {
                      "Entity": "Listings"
                    }
                  },
                  "Property": "BedBand"
                }
              },
              "queryRef": "Listings.BedBand",
              "nativeQueryRef": "BedBand",
              "active": true
            }
          ]
        }
      }
    },
    "objects": {
      "data": [
        {
          "properties": {
            "mode": {
              "expr": {
                "Literal": {
                  "Value": "'Between'"
                }
              }
            }
          }
        }
      ],
      "general": [
        {
          "properties": {}
        }
      ]
    },
    "visualContainerObjects": {
      "border": [
        {
          "properties": {
            "show": {
              "expr": {
                "Literal": {
                  "Value": "true"
                }
              }
            },
            "color": {
              "solid": {
                "color": {
                  "expr": {
                    "ThemeDataColor": {
                      "ColorId": 0,
                      "Percent": 0
                    }
                  }
                }
              }
            },
            "radius": {
              "expr": {
                "Literal": {
                  "Value": "15D"
                }
              }
            }
          }
        }
      ]
    },
    "syncGroup": {
      "groupName": "BedBand",
      "fieldChanges": true,
      "filterChanges": true
    },
    "drillFilterOtherVisuals": true
  }
}